VGAtil/VGAtil.py
VGAtil/__init__.py
VGAtil/demo_VGAtil.py
VGAtil-1.5.4.dist-info/METADATA
VGAtil-1.5.4.dist-info/WHEEL
VGAtil-1.5.4.dist-info/top_level.txt
VGAtil-1.5.4.dist-info/RECORD
